imio.dms.soap2pm-0.5-py3.11-nspkg.pth
imio/dms/soap2pm/__init__.py
imio/dms/soap2pm/configure.zcml
imio/dms/soap2pm/interfaces.py
imio/dms/soap2pm/setuphandlers.py
imio/dms/soap2pm/testing.py
imio/dms/soap2pm/testing.zcml
imio/dms/soap2pm/browser/__init__.py
imio/dms/soap2pm/browser/configure.zcml
imio/dms/soap2pm/browser/views.py
imio/dms/soap2pm/browser/static/.gitkeep
imio/dms/soap2pm/content/__init__.py
imio/dms/soap2pm/content/configure.zcml
imio/dms/soap2pm/locales/imio.dms.soap2pm.pot
imio/dms/soap2pm/locales/update.sh
imio/dms/soap2pm/locales/fr/LC_MESSAGES/imio.dms.soap2pm.po
imio/dms/soap2pm/profiles/default/browserlayer.xml
imio/dms/soap2pm/profiles/default/imiodmssoap2pm_marker.txt
imio/dms/soap2pm/profiles/default/metadata.xml
imio/dms/soap2pm/profiles/testing/metadata.xml
imio/dms/soap2pm/profiles/uninstall/browserlayer.xml
imio/dms/soap2pm/profiles/uninstall/metadata.xml
imio/dms/soap2pm/tests/__init__.py
imio/dms/soap2pm/tests/test_robot.py
imio/dms/soap2pm/tests/test_setup.py
imio/dms/soap2pm/tests/robot/.gitkeep
imio.dms.soap2pm-0.5.dist-info/METADATA
imio.dms.soap2pm-0.5.dist-info/WHEEL
imio.dms.soap2pm-0.5.dist-info/entry_points.txt
imio.dms.soap2pm-0.5.dist-info/namespace_packages.txt
imio.dms.soap2pm-0.5.dist-info/top_level.txt
imio.dms.soap2pm-0.5.dist-info/RECORD
