Metadata-Version: 2.1
Name: imio.dms.soap2pm
Version: 0.5
Summary: Dsm soap client method
Home-page: https://github.com/imio/imio.dms.soap2pm
Download-URL: https://devpi.imio.be/root/imio/imio.dms.soap2pm
Author: sgeulette
Author-email: support@imio.be
License: GPL
Keywords: dms document management system soap
Classifier: Development Status :: 5 - Production/Stable
Classifier: Environment :: Web Environment
Classifier: Framework :: Plone
Classifier: Framework :: Plone :: 4.3
Classifier: License :: OSI Approved :: GNU General Public License v2 (GPLv2)
Classifier: Programming Language :: Python
Classifier: Programming Language :: Python :: 2.7
Classifier: Operating System :: OS Independent
Requires-Dist: five.grok
Requires-Dist: plone.api
Requires-Dist: setuptools
Requires-Dist: imio.dms.mail
Requires-Dist: imio.helpers
Requires-Dist: imio.pm.wsclient
Provides-Extra: test
Requires-Dist: ecreall.helpers.testing ; extra == 'test'
Requires-Dist: plone.app.testing ; extra == 'test'
Requires-Dist: plone.app.robotframework ; extra == 'test'
